setup.py
rsync4python/__init__.py
rsync4python/rdiff.py
rsync4python/rsync.c
rsync4python/shell.py
rsync4python.egg-info/PKG-INFO
rsync4python.egg-info/SOURCES.txt
rsync4python.egg-info/dependency_links.txt
rsync4python.egg-info/entry_points.txt
rsync4python.egg-info/not-zip-safe
rsync4python.egg-info/top_level.txt
rsync4python/tests/__init__.py