Metadata-Version: 1.0
Name: rsync4python
Version: 0.2
Summary: rsync4python - rsync access for python
Home-page: https://github.com/BenjamenMeyer/rsync4python
Author: Rackspace
Author-email: ben.meyer@rackspace.com
License: Apache License 2.0
Platform: UNKNOWN
